count_unique_characters/__init__.py
count_unique_characters/core.py
count_unique_characters-0.1.3.dist-info/licenses/LICENSE
count_unique_characters-0.1.3.dist-info/METADATA
count_unique_characters-0.1.3.dist-info/WHEEL
count_unique_characters-0.1.3.dist-info/entry_points.txt
count_unique_characters-0.1.3.dist-info/top_level.txt
count_unique_characters-0.1.3.dist-info/RECORD
