Metadata-Version: 2.4
Name: count_unique_characters
Version: 0.1.3
Summary: A package to count unique characters in a string.
Author-email: Yurii Stepanenko <Step.crypt@gmail.com>
License: MIT License
Requires-Python: >=3.7
License-File: LICENSE
Dynamic: license-file
